{
  "_class": "shapeGroup",
  "clippingMaskMode": 0,
  "do_objectID": "BE48A105-DC98-4CAE-8B2D-77502D4ECE31",
  "exportOptions": {
    "_class": "exportOptions",
    "exportFormats": [
    ],
    "includedLayerIds": [
    ],
    "layerOptions": 0,
    "shouldTrim": false
  },
  "frame": {
    "_class": "rect",
    "constrainProportions": false,
    "height": 12,
    "width": 13.212890625,
    "x": 1042,
    "y": 543
  },
  "hasClickThrough": false,
  "hasClippingMask": false,
  "isFlippedHorizontal": false,
  "isFlippedVertical": false,
  "isLocked": false,
  "isVisible": true,
  "layerListExpandedType": 0,
  "layers": [
    {
      "class": "shapePath",
      "id": "93766163-25E6-4A90-8042-E7F2FBFF2987"
    },
    {
      "class": "shapePath",
      "id": "B8A3BB37-4467-43CA-96D3-203B48A1B9F4"
    },
    {
      "class": "shapePath",
      "id": "C9EC4A99-7162-4FE6-822D-B0FAA0C2F213"
    },
    {
      "class": "shapePath",
      "id": "267B0963-C6C5-4888-8DEE-019B0EAE6328"
    },
    {
      "class": "shapePath",
      "id": "F3ABD168-8899-4A13-84D0-8B2974D4EF9A"
    }
  ],
  "name": "garbage",
  "nameIsFixed": true,
  "resizingConstraint": 63,
  "resizingType": 0,
  "rotation": 0,
  "shouldBreakMaskChain": false,
  "style": {
    "_class": "style",
    "blur": {
      "_class": "blur",
      "center": "{0.5, 0.5}",
      "isEnabled": false,
      "motionAngle": 0,
      "radius": 5,
      "type": 0
    },
    "endDecorationType": 0,
    "fills": [
      {
        "_class": "fill",
        "color": {
          "_class": "color",
          "alpha": 1,
          "blue": 0.2,
          "green": 0.2,
          "red": 0.2
        },
        "fillType": 0,
        "isEnabled": true,
        "noiseIndex": 0,
        "noiseIntensity": 0,
        "patternFillType": 1,
        "patternTileScale": 1
      }
    ],
    "miterLimit": 10,
    "startDecorationType": 0
  },
  "windingRule": 1
}